django_kiwi/__init__.py
django_kiwi/admin.py
django_kiwi/apps.py
django_kiwi/base_task.py
django_kiwi/consumer.py
django_kiwi/models.py
django_kiwi/producer.py
django_kiwi/settings.py
django_kiwi/tests.py
django_kiwi/urls.py
django_kiwi/views.py
django_kiwi/management/commands/consumesimplequeue.py
django_kiwi/migrations/0001_initial.py
django_kiwi/migrations/0002_task_name.py
django_kiwi/migrations/0003_auto_20200820_1403.py
django_kiwi/migrations/__init__.py
django_kiwi/tasks/__init__.py
django_kiwi/tasks/sample_task.py
django_kiwi/utils/__init__.py
django_kiwi/utils/packages.py
django_kiwi-0.0.1.dist-info/LICENSE
django_kiwi-0.0.1.dist-info/METADATA
django_kiwi-0.0.1.dist-info/README.md
django_kiwi-0.0.1.dist-info/WHEEL
django_kiwi-0.0.1.dist-info/top_level.txt
django_kiwi-0.0.1.dist-info/RECORD
