Metadata-Version: 2.1
Name: django-kiwi
Version: 0.0.1
Summary: a package to help developers work with queue situations
Home-page: https://gitlab.com/luisccf/django-kiwi.git
Author: Luis Carlos Cardoso
Author-email: luisccf@me.com
License: BSD-3-Clause
Platform: UNKNOWN
Classifier: Programming Language :: Python :: 3
Classifier: License :: OSI Approved :: MIT License
Classifier: Operating System :: OS Independent
Requires-Python: >=3.6
License-File: LICENSE
